scrapy_athlinks/__init__.py
scrapy_athlinks/items.py
scrapy_athlinks/pipelines.py
scrapy_athlinks/settings.py
scrapy_athlinks/spiders/__init__.py
scrapy_athlinks/spiders/race.py
scrapy_athlinks-0.0.1.dist-info/LICENSE
scrapy_athlinks-0.0.1.dist-info/METADATA
scrapy_athlinks-0.0.1.dist-info/WHEEL
scrapy_athlinks-0.0.1.dist-info/top_level.txt
scrapy_athlinks-0.0.1.dist-info/RECORD
