Metadata-Version: 2.1
Name: scrapy-athlinks
Version: 0.0.1
Summary: Web scraper for race results hosted on Athlinks.
Home-page: https://github.com/aaron-schroeder/athlinks-scraper-scrapy
Author: Aaron Schroeder
Author-email: aaron@trailzealot.com
License: MIT
Platform: UNKNOWN
Classifier: License :: OSI Approved :: MIT License
Classifier: Intended Audience :: Developers
Classifier: Programming Language :: Python :: 3
Classifier: Programming Language :: Python :: 3.8
Requires-Dist: Scrapy (==2.6.2)
